Workbook

Sheet 📊 Dashboard
A1: 💰 TOTAL SPENDING DASHBOARD
A2: User Name → | B2: Enter Your Name
A4: Category | B4: Amount (₹)
A5: 🍽️ Mess Expenses | B5: ='Mess Expenses'!F20
A6: 🏪 Outside Spending | B6: ='Outside Spending'!C18
A7: 🏠 Rent / Bills / Fees | B7: ='Rent Bills Fees'!C9
A8: 🎉 Friends / Fest Pays | B8: ='Friends Pays'!D15
A9: 📦 Others | B9: ='Others'!C15
A10: 💰 GRAND TOTAL | B10: =SUM(B5:B9)
A12: ℹ️ Debts tracker is in the 'Debts Borrowing' sheet

Sheet Mess Expenses
A1: 🍽️ MESS EXPENSES
A3: Date | B3: Food Item | C3: Food Price (₹) | D3: Extra Item | E3: Extra Price (₹) | F3: Total (₹)
F4: =IF(C4="","",C4+IF(E4="",0,E4))
F5: =IF(C5="","",C5+IF(E5="",0,E5))
F6: =IF(C6="","",C6+IF(E6="",0,E6))
F7: =IF(C7="","",C7+IF(E7="",0,E7))
F8: =IF(C8="","",C8+IF(E8="",0,E8))
F9: =IF(C9="","",C9+IF(E9="",0,E9))
F10: =IF(C10="","",C10+IF(E10="",0,E10))
F11: =IF(C11="","",C11+IF(E11="",0,E11))
F12: =IF(C12="","",C12+IF(E12="",0,E12))
F13: =IF(C13="","",C13+IF(E13="",0,E13))
F14: =IF(C14="","",C14+IF(E14="",0,E14))
F15: =IF(C15="","",C15+IF(E15="",0,E15))
... F19: =IF(C19="","",C19+IF(E19="",0,E19))
E20: TOTAL SPENDING | F20: =SUM(F4:F19)

Sheet Outside Spending
A1: 🏪 OUTSIDE MESS SPENDING
A2: 🍔 Food (Outside) | E2: 🛍️ Shopping
A3: Date | B3: Food Item | C3: Price (₹) | E3: Date | F3: Item Bought | G3: Price (₹)
B16: Food Total | C16: =SUM(C4:C15) | F16: Shopping Total | G16: =SUM(G4:G15)
A18: OUTSIDE TOTAL SPENDING | C18: =C16+G16

Sheet Rent Bills Fees
A1: 🏠 RENT / BILLS / FEES
A2: Category | B2: Description | C2: Amount (₹)
A3: Rent | B3: Monthly Room Rent
A4: Electricity Bill | B4: Monthly Bill
A5: Water Bill | B5: Monthly Bill
A6: Internet / Wifi | B6: Monthly Bill
A7: College Fees | B7: Semester/Year Fees
A8: Other Fees | B8: Miscellaneous
B9: TOTAL | C9: =SUM(C3:C8)

Sheet Friends Pays
A1: 🎉 FRIENDS / FESTIVAL / COLLEGE FEST PAYMENTS
A2: Date | B2: Event / Festival | C2: Paid For (Name) | D2: Amount (₹)
C15: TOTAL | D15: =SUM(D3:D14)

Sheet Debts Borrowing
A1: 💸 DEBTS & BORROWING TRACKER
A2: Friend Name | B2: Total Amount (₹) | C2: Amount Remaining (₹) | D2: Who Pays Whom | E2: Status
E3: =IF(C3=0,"✅ Cleared","⏳ Pending")
E4: =IF(C4=0,"✅ Cleared","⏳ Pending")
E5: =IF(C5=0,"✅ Cleared","⏳ Pending")
E6: =IF(C6=0,"✅ Cleared","⏳ Pending")
E7: =IF(C7=0,"✅ Cleared","⏳ Pending")
E8: =IF(C8=0,"✅ Cleared","⏳ Pending")
E9: =IF(C9=0,"✅ Cleared","⏳ Pending")
E10: =IF(C10=0,"✅ Cleared","⏳ Pending")
E11: =IF(C11=0,"✅ Cleared","⏳ Pending")
E12: =IF(C12=0,"✅ Cleared","⏳ Pending")
E13: =IF(C13=0,"✅ Cleared","⏳ Pending")
E14: =IF(C14=0,"✅ Cleared","⏳ Pending")

Sheet Others
A1: 📦 OTHERS / MISCELLANEOUS
A2: Date | B2: Description | C2: Amount (₹)
B15: TOTAL | C15: =SUM(C3:C14)
